GraphifyPy/UndirectedGraphs.py
GraphifyPy/__init__.py
graphifypy-0.0.7.dist-info/WHEEL
graphifypy-0.0.7.dist-info/METADATA
graphifypy-0.0.7.dist-info/RECORD
