Metadata-Version: 2.1
Name: GraphifyPy
Version: 0.0.7
Summary: A library for different graph functionalities and operations.
Author-email: advaitmenon1106 <advaitmenon1106@gmail.com>
Requires-Python: >=3.7
Classifier: Programming Language :: Python :: 3
Classifier: License :: OSI Approved :: MIT License
Classifier: Operating System :: OS Independent
Project-URL: Homepage, https://github.com/Advaitmenon1106/GraphifyPy.git
